LICENSE
MANIFEST.in
README.md
VERSION
setup.cfg
setup.py
src/permifrost/__init__.py
src/permifrost/entities.py
src/permifrost/error.py
src/permifrost/logger.py
src/permifrost/snowflake_connector.py
src/permifrost/snowflake_grants.py
src/permifrost/snowflake_permission.py
src/permifrost/snowflake_role_grant_checker.py
src/permifrost/snowflake_spec_loader.py
src/permifrost/spec_file_loader.py
src/permifrost/types.py
src/permifrost.egg-info/PKG-INFO
src/permifrost.egg-info/SOURCES.txt
src/permifrost.egg-info/dependency_links.txt
src/permifrost.egg-info/entry_points.txt
src/permifrost.egg-info/requires.txt
src/permifrost.egg-info/top_level.txt
src/permifrost/cli/__init__.py
src/permifrost/cli/__main__.py
src/permifrost/cli/cli.py
src/permifrost/cli/permissions.py
src/permifrost/spec_schemas/__init__.py
src/permifrost/spec_schemas/snowflake.py