Metadata-Version: 2.1
Name: permifrost
Version: 0.15.1
Summary: Permifrost Permissions
Home-page: https://gitlab.com/gitlab-data/permifrost
Author: GitLab Data Team, Meltano Team, & Contributors
Author-email: permifrost@gitlab.com
License: UNKNOWN
Platform: UNKNOWN
Classifier: Programming Language :: Python :: 3
Classifier: License :: OSI Approved :: MIT License
Classifier: Operating System :: OS Independent
Provides-Extra: dev
License-File: LICENSE
